{"list":[{"date":"2017-05","arr":{"year":2017,"month":5,"link":["2017-05-16_讨论项目方案1.jpg","2017-05-16_讨论项目方案2.jpg"],"text":["讨论项目方案1","讨论项目方案2"],"type":["image","image"]}},{"date":"2016-10","arr":{"year":2016,"month":10,"link":["2016-10-16_羽良招聘线下宣传（激光雷达新型交互屏）.jpg"],"text":["羽良招聘线下宣传（激光雷达新型交互屏）"],"type":["image"]}},{"date":"2016-09","arr":{"year":2016,"month":9,"link":["2016-09-03_激光雷达坦克车.png","2016-09-03_激光雷达坦克车（侧面）.png","2016-09-30_新生教学项目（自制游戏手柄）.jpg"],"text":["激光雷达坦克车","激光雷达坦克车（侧面）","新生教学项目（自制游戏手柄）"],"type":["image","image","image"]}},{"date":"2016-08","arr":{"year":2016,"month":8,"link":["2016-08-22_三维重建无人机.png","2016-08-23_光电所科创计划结题.jpg"],"text":["三维重建无人机","光电所科创计划结题"],"type":["image","image"]}},{"date":"2016-07","arr":{"year":2016,"month":7,"link":["2016-07-29_光电设计大赛决赛.jpg","2016-07-29_光电设计大赛决赛2.jpg"],"text":["光电设计大赛决赛","光电设计大赛决赛2"],"type":["image","image"]}},{"date":"2016-05","arr":{"year":2016,"month":5,"link":["2016-05-23_校赛前夜.jpg","2016-05-30_接受校报采访.jpg"],"text":["校赛前夜","接受校报采访"],"type":["image","image"]}},{"date":"2016-04","arr":{"year":2016,"month":4,"link":["2016-04-04_YOCSEF.jpg","2016-04-23_长春光机所.jpg","2016-04-27_实验室.jpg","2016-04-30_科技部内部技术分享.jpg"],"text":["YOCSEF","长春光机所","实验室","科技部内部技术分享"],"type":["image","image","image","image"]}},{"date":"2015-10","arr":{"year":2015,"month":10,"link":["2015-10-14_光电设计大赛校赛.jpg"],"text":["光电设计大赛校赛"],"type":["image"]}},{"date":"2015-07","arr":{"year":2015,"month":7,"link":["2015-07-05_长春光机所.jpg"],"text":["长春光机所"],"type":["image"]}},{"date":"2015-05","arr":{"year":2015,"month":5,"link":["2015-05-01_羽良科技部合照.jpg"],"text":["羽良科技部合照"],"type":["image"]}},{"date":"2015-04","arr":{"year":2015,"month":4,"link":["2015-04-06_跟踪人脸摄像头.jpg"],"text":["跟踪人脸摄像头"],"type":["image"]}}]}